{
  "rep": 1200,
  "rewards_per_monster": {
    "Creeper": [
      -1680.0,
      1706.0,
      1718.0,
      1728.0,
      1830.0,
      1720.0,
      -1474.0,
      1802.0,
      1724.0,
      1728.0,
      1758.0,
      1588.0,
      -1488.0,
      1728.0,
      1890.0,
      1818.0,
      1754.0,
      1802.0,
      -1332.0,
      1848.0,
      -1550.0,
      1670.0
    ],
    "Spider": [
      2072.0,
      2360.0,
      2196.0,
      2176.0,
      2134.0,
      2174.0,
      2112.0,
      2100.0,
      2030.0,
      2294.0,
      2312.0,
      2252.0,
      2240.0,
      2240.0,
      2336.0,
      2320.0,
      2264.0,
      2282.0,
      2264.0,
      2316.0,
      2296.0,
      2070.0,
      2356.0,
      2176.0,
      1968.0,
      1928.0
    ],
    "Zombie": [
      -666.0,
      2482.0,
      2454.0,
      -1224.0,
      -942.0,
      2434.0,
      2416.0,
      1866.0,
      -1344.0,
      2086.0,
      2078.0,
      2368.0,
      2366.0,
      2200.0,
      2146.0,
      -1016.0,
      2082.0,
      -750.0,
      -966.0,
      -844.0,
      2368.0,
      2148.0,
      2356.0,
      -1176.0,
      -1452.0,
      -2190.0,
      -1142.0
    ],
    "Skeleton": [
      -1140.0,
      2522.0,
      -1318.0,
      -1210.0,
      -1198.0,
      -1486.0,
      -1244.0,
      2426.0,
      2296.0,
      -1510.0,
      2476.0,
      -926.0,
      -1084.0,
      -1078.0,
      -1226.0,
      -1118.0,
      -2688.0,
      2244.0,
      -888.0,
      2216.0,
      2366.0,
      2412.0,
      2452.0,
      2290.0,
      2310.0
    ]
  },
  "attacks_per_monster": {
    "Creeper": [
      16,
      17,
      3,
      3,
      10,
      5,
      27,
      27,
      4,
      3,
      17,
      3,
      29,
      3,
      10,
      19,
      10,
      12,
      35,
      8,
      5,
      5
    ],
    "Spider": [
      74,
      15,
      41,
      59,
      55,
      50,
      64,
      52,
      81,
      25,
      17,
      32,
      40,
      30,
      16,
      25,
      24,
      28,
      29,
      16,
      16,
      81,
      11,
      48,
      90,
      105
    ],
    "Zombie": [
      30,
      23,
      36,
      102,
      99,
      44,
      41,
      162,
      93,
      116,
      112,
      53,
      55,
      101,
      119,
      38,
      111,
      27,
      54,
      61,
      53,
      93,
      41,
      93,
      57,
      60,
      56
    ],
    "Skeleton": [
      36,
      22,
      68,
      43,
      86,
      77,
      27,
      21,
      62,
      38,
      36,
      60,
      76,
      62,
      107,
      87,
      18,
      71,
      79,
      77,
      52,
      48,
      22,
      61,
      47
    ]
  },
  "remaining_agent_hp_per_monster": {
    "Creeper": [
      0,
      15.0,
      19.0,
      20.0,
      9.0,
      20.0,
      0,
      13.0,
      20.0,
      20.0,
      19.0,
      6.0,
      0,
      20.0,
      15.0,
      6.0,
      20.0,
      19.0,
      0,
      10.0,
      0,
      15.0
    ],
    "Spider": [
      12.0,
      16.0,
      10.0,
      14.0,
      10.0,
      12.0,
      12.0,
      6.0,
      10.0,
      14.0,
      12.0,
      12.0,
      14.0,
      10.0,
      14.0,
      16.0,
      10.0,
      14.0,
      12.0,
      12.0,
      10.0,
      14.0,
      14.0,
      12.0,
      8.0,
      10.0
    ],
    "Zombie": [
      0,
      8.0,
      11.0,
      0,
      0,
      11.0,
      8.0,
      2.0,
      0,
      5.0,
      2.0,
      8.0,
      8.0,
      11.0,
      11.0,
      0,
      2.0,
      0,
      0,
      0,
      8.0,
      2.0,
      2.0,
      0,
      0,
      11.0,
      0
    ],
    "Skeleton": [
      0,
      11.0,
      0,
      0,
      0,
      0,
      0,
      1.0,
      5.0,
      0,
      12.0,
      0,
      0,
      0,
      0,
      0,
      5.0,
      4.0,
      0,
      3.0,
      8.0,
      11.0,
      4.0,
      4.0,
      1.0
    ]
  },
  "winrates_per_monster": {
    "Creeper": [
      17,
      22
    ],
    "Spider": [
      26,
      26
    ],
    "Zombie": [
      15,
      27
    ],
    "Skeleton": [
      11,
      25
    ]
  }
}